importo/__init__.py
importo/apps.py
importo/commands.py
importo/constants.py
importo/finders.py
importo/lookups.py
importo/models.py
importo/test_commands.py
importo/fields/__init__.py
importo/fields/base.py
importo/fields/constants.py
importo/fields/datetime.py
importo/fields/error_codes.py
importo/fields/file.py
importo/fields/html.py
importo/fields/related.py
importo/fields/strategy_codes.py
importo/fields/struct.py
importo/fields/typed.py
importo/parsers/__init__.py
importo/parsers/base.py
importo/readers/__init__.py
importo/readers/base.py
importo/readers/csv.py
importo/readers/db.py
importo/readers/errors.py
importo/readers/json.py
importo/readers/test_base.py
importo/readers/test_csv.py
importo/readers/test_db.py
importo/static/importo/dummy_files/dummy.pdf
importo/static/importo/dummy_files/dummy.png
importo/utils/__init__.py
importo/utils/classes.py
importo/utils/datetime.py
importo/utils/html.py
importo/utils/io.py
importo/utils/query.py
importo/utils/url.py
importo/utils/values.py
importo/wagtail/blocks.py
importo/wagtail/commands.py
importo/wagtail/finders.py
importo/wagtail/lookups.py
importo/wagtail/models.py
importo/wagtail/fields/__init__.py
importo/wagtail/fields/file.py
importo/wagtail/fields/related.py
importo/wagtail/fields/richtext.py
importo/wagtail/fields/streamfield.py
importo/wagtail/parsers/__init__.py
importo/wagtail/parsers/footnotes.py
importo/wagtail/parsers/richtext.py
importo/wagtail/parsers/streamfield.py
importo/wagtail/utils/query.py
django_importo-0.1.0.dist-info/LICENSE
django_importo-0.1.0.dist-info/METADATA
django_importo-0.1.0.dist-info/WHEEL
django_importo-0.1.0.dist-info/top_level.txt
django_importo-0.1.0.dist-info/RECORD
