Metadata-Version: 2.1
Name: django-importo
Version: 0.1.0
Summary: UNKNOWN
Home-page: UNKNOWN
Author: Andy Babic
Author-email: andyjbabic@gmail.com
License: BSD-3-Clause
Keywords: django migrate legacy data import wagtail pages models utility
Platform: UNKNOWN
Classifier: Environment :: Web Environment
Classifier: Development Status :: 1 - Planning
Classifier: Intended Audience :: Developers
Classifier: Operating System :: OS Independent
Classifier: License :: OSI Approved :: BSD License
Classifier: Natural Language :: English
Classifier: Programming Language :: Python
Classifier: Programming Language :: Python :: 3.7
Classifier: Programming Language :: Python :: 3.8
Classifier: Programming Language :: Python :: 3.9
Classifier: Framework :: Django
Classifier: Framework :: Django :: 2.2
Classifier: Framework :: Django :: 3.1
Classifier: Framework :: Django :: 3.2
Classifier: Framework :: Wagtail
Classifier: Framework :: Wagtail :: 2
Requires-Python: >=3.6
License-File: LICENSE
Requires-Dist: Django (>=2.2)
Provides-Extra: lint
Requires-Dist: black (==21.7b0) ; extra == 'lint'
Requires-Dist: isort (==5.9.3) ; extra == 'lint'
Requires-Dist: flake8 (==3.9.2) ; extra == 'lint'
Provides-Extra: test
Requires-Dist: pytest-cov (==2.12.1) ; extra == 'test'
Requires-Dist: pytest-mock (==3.6.1) ; extra == 'test'
Requires-Dist: pytest-django (==4.4.0) ; extra == 'test'
Requires-Dist: pytest (==6.2.4) ; extra == 'test'
